{
  "kind": "singleType",
  "collectionName": "heroes",
  "info": {
    "name": "Hero"
  },
  "options": {
    "increments": true,
    "timestamps": true,
    "draftAndPublish": true
  },
  "pluginOptions": {},
  "attributes": {
    "title": {
      "type": "string",
      "required": true
    },
    "subtitle": {
      "type": "string",
      "required": false
    },
    "background": {
      "model": "file",
      "via": "related",
      "allowedTypes": [
        "images"
      ],
      "plugin": "upload",
      "required": true,
      "pluginOptions": {}
    }
  }
}
